setup.py
embtechx/__init__.py
embtechx/dataframe.py
embtechx/embedding.py
embtechx/evaluate.py
embtechx/search.py
embtechx.egg-info/PKG-INFO
embtechx.egg-info/SOURCES.txt
embtechx.egg-info/dependency_links.txt
embtechx.egg-info/requires.txt
embtechx.egg-info/top_level.txt