Metadata-Version: 2.1
Name: embtechx
Version: 1.0.9
Requires-Dist: sentence-transformers
Requires-Dist: torch
Requires-Dist: pandas
Requires-Dist: IPython
Requires-Dist: langdetect
Requires-Dist: scikit-learn
Requires-Dist: seaborn
Requires-Dist: matplotlib
